{
  "id": "fence_female_v11",
  "display_name": "Fence (F) (variant 11)",
  "tags": [
    "medieval",
    "outlaw"
  ],
  "layers": {
    "body": "body/bodies/female/walk.png",
    "head": "head/heads/human/female/walk.png",
    "eyes": "eyes/human/adult/default/walk.png",
    "feet": "feet/boots/revised/thin/walk/blue.png",
    "legs": "legs/formal/thin/walk/tan.png",
    "torso": "torso/aprons/apron_full/female/walk/green.png",
    "hair": "hair/extensions/bangs/long_straightr/adult/walk.png",
    "weapon": "weapon/blunt/flail/behind/walk/flail.png",
    "waist": "torso/waist/belt_formal/walk/brown.png",
    "hat": "hat/cloth/bandana2/adult/walk/slate.png",
    "facial": "facial/glasses/secretary/adult/walk/leather.png",
    "arms": "arms/armour/plate/thin/walk.png"
  },
  "tints": {
    "body": "#f2c7a5",
    "head": "#f2c7a5",
    "hair": "#9a693b",
    "beard": "#9a693b"
  },
  "animations": [
    "walk",
    "idle"
  ]
}