{
  "id": "merchant_male_v20",
  "display_name": "Travelling Merchant (variant 20)",
  "tags": [
    "medieval",
    "wayfarer"
  ],
  "layers": {
    "body": "body/bodies/male/walk.png",
    "head": "head/heads/human/male/walk.png",
    "eyes": "eyes/human/adult/default/walk.png",
    "feet": "feet/boots/basic/male/walk/slate.png",
    "legs": "legs/formal/male/walk/base.png",
    "torso": "torso/aprons/apron/male/walk/orange.png",
    "hair": "hair/idol/adult/walk.png",
    "waist": "torso/waist/obi/male/walk/blue.png",
    "hat": "hat/cloth/bandana/adult/walk/navy.png",
    "backpack": "backpack/straps/male/walk/yellow.png"
  },
  "tints": {
    "body": "#a86b47",
    "head": "#a86b47",
    "hair": "#9a693b",
    "beard": "#9a693b"
  },
  "animations": [
    "walk",
    "idle"
  ]
}